daemon_and_webui/mlogger_daemon_filter_ui.py
daemon_and_webui/mloggerai_daemon.py
daemon_and_webui/mloggerai_daemon_with_filter.py
daemon_and_webui/mloggerai_docker_daemon.py
daemon_and_webui/mloggerai_docker_daemon_filtered_ui.py
daemon_and_webui/mloggerai_docker_daemon_filtered_ui_bis.py
daemon_and_webui/mloggerai_docker_daemon_ui.py
mloggerai/__init__.py
mloggerai/errorsolver.py
mloggerai/errorsolverbuilder.py
tests/test_errorsolver.py
tests/test_errorsolverbuilder.py
mloggerai-0.0.0.dev8.dist-info/METADATA
mloggerai-0.0.0.dev8.dist-info/WHEEL
mloggerai-0.0.0.dev8.dist-info/top_level.txt
mloggerai-0.0.0.dev8.dist-info/RECORD
