Metadata-Version: 2.4
Name: mloggerai
Version: 0.0.0.dev8
Summary: MLoggerAI: AI-powered Python traceback analyzer
Author: Mirko Perrone
License-Expression: MIT
Project-URL: Homepage, https://github.com/perronemirko/mloggerai
Project-URL: Issues, https://github.com/perronemirko/mloggerai/issues
Requires-Python: >=3.10
Requires-Dist: openai>=1.109.1
Requires-Dist: python-dotenv>=1.1.1
